{
  "greeting": "晚上好",
  "name": "毛小瑜",
  "greetingText": "我的船长",
  "wishText": "希望你能够永远：一点浩然气，千里快哉风 ;)",
  "imagePath": "img/hijack.png",
  "text1": "生日快乐 :D",
  "textInChatBox": "感谢你一直以来对我的支持，小瑜，这一年，你辛苦了",
  "sendButtonLabel": "摸摸~",
  "text2": "我们已经一起走过了很远。但是，属于我们真正的旅途还未开始",
  "text3": "当然，也包括那些，未来永远无法击垮我们的困难",
  "text4": "在踏上这段旅程之前，海德拉想把自己一直坚信的",
  "text4Adjective": "勇气",
  "text5Entry": "分享给你。因为 --",
  "text5Content": "你是我最珍视的宝物",
  "smiley": ":)",
  "bigTextPart1": "那么",
  "bigTextPart2": "我亲爱的小瑜",
  "wishHeading": "祝你生日快乐",
  "outroText": "我会陪你一直走下去",
  "replayText": "直到你用这个名字，写下这一生，你想用文字去记录的一切",
  "outroSmiley": ":)"
}
